tttk.py
tttk-1.0.4.dist-info/LICENCE.MPL
tttk-1.0.4.dist-info/LICENSE.996ICU
tttk-1.0.4.dist-info/METADATA
tttk-1.0.4.dist-info/WHEEL
tttk-1.0.4.dist-info/top_level.txt
tttk-1.0.4.dist-info/zip-safe
tttk-1.0.4.dist-info/RECORD
