Metadata-Version: 2.1
Name: tttk
Version: 1.0.4
Summary: tkinter的增强库
Home-page: https://github.com/TotoWang-hhh/tttk/
Download-URL: https://github.com/TotoWang-hhh/tttk/archive/master.zip
Author: 真_人工智障（rgzz666）
Author-email: tt1224@hotmail.com
License: MPL 2.0
Keywords: tttk,tkinter增强,tk增强
License-File: LICENCE.MPL
License-File: LICENSE.996ICU
